Metadata-Version: 2.1
Name: video-marker
Version: 0.6.1
Summary: OpenCV based video Marker utility
Home-page: https://github.com/peppelinux/video-marker
Author: Giuseppe De Marco
Author-email: demarcog83@gmail.com
License: License :: OSI Approved :: European Union Public Licence 1.2 (EUPL 1.2)
Platform: UNKNOWN
Classifier: Development Status :: 5 - Production/Stable
Classifier: License :: OSI Approved :: European Union Public Licence 1.2 (EUPL 1.2)
Classifier: Programming Language :: Python :: 3
License-File: LICENSE
